INSTALL.rst
LICENSE
MANIFEST.in
README.rst
setup.cfg
setup.py
django_richtemplates.egg-info/PKG-INFO
django_richtemplates.egg-info/SOURCES.txt
django_richtemplates.egg-info/dependency_links.txt
django_richtemplates.egg-info/not-zip-safe
django_richtemplates.egg-info/requires.txt
django_richtemplates.egg-info/top_level.txt
docs/.configuration.rst.swp
docs/Makefile
docs/conf.py
docs/configuration.rst
docs/documentation_guidelines.rst
docs/forms.rst
docs/index.rst
docs/installation.rst
docs/make.bat
docs/management.rst
docs/middleware.rst
docs/quickstart.rst
docs/screenshots.rst
docs/skins.rst
docs/templates.rst
docs/userprofiles.rst
docs/_build/doctrees/configuration.doctree
docs/_build/doctrees/documentation_guidelines.doctree
docs/_build/doctrees/environment.pickle
docs/_build/doctrees/forms.doctree
docs/_build/doctrees/index.doctree
docs/_build/doctrees/installation.doctree
docs/_build/doctrees/management.doctree
docs/_build/doctrees/middleware.doctree
docs/_build/doctrees/quickstart.doctree
docs/_build/doctrees/screenshots.doctree
docs/_build/doctrees/skins.doctree
docs/_build/doctrees/templates.doctree
docs/_build/doctrees/userprofiles.doctree
docs/_build/doctrees/api/index.doctree
docs/_build/doctrees/api/widgets.doctree
docs/_build/html/.buildinfo
docs/_build/html/configuration.html
docs/_build/html/documentation_guidelines.html
docs/_build/html/forms.html
docs/_build/html/genindex.html
docs/_build/html/index.html
docs/_build/html/installation.html
docs/_build/html/management.html
docs/_build/html/middleware.html
docs/_build/html/objects.inv
docs/_build/html/py-modindex.html
docs/_build/html/quickstart.html
docs/_build/html/screenshots.html
docs/_build/html/search.html
docs/_build/html/searchindex.js
docs/_build/html/skins.html
docs/_build/html/templates.html
docs/_build/html/userprofiles.html
docs/_build/html/_images/richtemplates-examples-home.png
docs/_build/html/_images/richtemplates-examples-messages.png
docs/_build/html/_images/richtemplates-login-page-with-errors.png
docs/_build/html/_images/richtemplates-login-page.png
docs/_build/html/_images/richtemplates-projector-project.png
docs/_build/html/_images/richtemplates-projector-task-update.png
docs/_build/html/_images/richtemplates-projector-task-updated.png
