Metadata-Version: 1.1
Name: django-richtemplates
Version: 0.3.12
Summary: 
